metricai_sdk/__init__.py
metricai_sdk/auth.py
metricai_sdk/client.py
metricai_sdk/config.py
metricai_sdk/errors.py
metricai_sdk/http.py
metricai_sdk/models/__init__.py
metricai_sdk/models/alert.py
metricai_sdk/models/api_keys.py
metricai_sdk/models/payment.py
metricai_sdk/models/pricing.py
metricai_sdk/models/provider.py
metricai_sdk/models/proxy.py
metricai_sdk/models/shared_api.py
metricai_sdk/models/stats.py
metricai_sdk/models/transaction.py
metricai_sdk/models/user.py
metricai_sdk/models/wallet.py
metricai_sdk/resources/__init__.py
metricai_sdk/resources/alerts.py
metricai_sdk/resources/api_keys.py
metricai_sdk/resources/health.py
metricai_sdk/resources/payments.py
metricai_sdk/resources/pricing.py
metricai_sdk/resources/providers.py
metricai_sdk/resources/proxy.py
metricai_sdk/resources/shared_api.py
metricai_sdk/resources/stats.py
metricai_sdk/resources/transactions.py
metricai_sdk/resources/user.py
metricai_sdk/resources/wallet.py
metricai_sdk_beta-1.0.2.dist-info/METADATA
metricai_sdk_beta-1.0.2.dist-info/WHEEL
metricai_sdk_beta-1.0.2.dist-info/top_level.txt
metricai_sdk_beta-1.0.2.dist-info/RECORD
