Metadata-Version: 2.4
Name: metricai-sdk-beta
Version: 1.0.2
Summary: Beta Python SDK for MetricAI API
Author-email: Krishna Dahale <krishna09dahale@gmail.com>
License: MIT
Project-URL: Homepage, https://github.com/metricai/metricai-sdk-python
Project-URL: Documentation, https://github.com/metricai/metricai-sdk-python/blob/main/README.md
Project-URL: Repository, https://github.com/metricai/metricai-sdk-python
Project-URL: Issues, https://github.com/metricai/metricai-sdk-python/issues
Keywords: metricai,llm,api,sdk,openai,claude,gemini
Classifier: Development Status :: 4 - Beta
Classifier: Intended Audience :: Developers
Classifier: License :: OSI Approved :: MIT License
Classifier: Programming Language :: Python :: 3
Classifier: Programming Language :: Python :: 3.8
Classifier: Programming Language :: Python :: 3.9
Classifier: Programming Language :: Python :: 3.10
Classifier: Programming Language :: Python :: 3.11
Classifier: Programming Language :: Python :: 3.12
Classifier: Topic :: Software Development :: Libraries :: Python Modules
Requires-Python: >=3.8
Requires-Dist: httpx>=0.24.0
Requires-Dist: pydantic>=2.0.0
Provides-Extra: dev
Requires-Dist: pytest>=7.0.0; extra == "dev"
Requires-Dist: pytest-cov>=4.0.0; extra == "dev"
Requires-Dist: pytest-mock>=3.10.0; extra == "dev"
Requires-Dist: black>=23.0.0; extra == "dev"
Requires-Dist: ruff>=0.1.0; extra == "dev"
Requires-Dist: mypy>=1.0.0; extra == "dev"
